{
    "ShapeName": "I_rotated_53",
    "Profile": [
        [
            -0.98,
            7.0
        ],
        [
            2.02,
            11.0
        ],
        [
            -9.95,
            20.02
        ],
        [
            -12.96,
            16.03
        ]
    ],
    "Midcurve": [
        [
            0.52,
            9.0
        ],
        [
            -11.46,
            18.03
        ]
    ],
    "Profile_lines": [
        [
            [
                -0.98,
                7.0
            ],
            [
                2.02,
                11.0
            ]
        ],
        [
            [
                2.02,
                11.0
            ],
            [
                -9.95,
                20.02
            ]
        ],
        [
            [
                -9.95,
                20.02
            ],
            [
                -12.96,
                16.03
            ]
        ],
        [
            [
                -12.96,
                16.03
            ],
            [
                -0.98,
                7.0
            ]
        ]
    ],
    "Midcurve_lines": [
        [
            [
                0.52,
                9.0
            ],
            [
                -11.46,
                18.03
            ]
        ]
    ]
}