{
    "ShapeName": "I_rotated_65",
    "Profile": [
        [
            -2.42,
            6.64
        ],
        [
            -0.31,
            11.18
        ],
        [
            -13.9,
            17.52
        ],
        [
            -16.01,
            12.98
        ]
    ],
    "Midcurve": [
        [
            -1.36,
            8.91
        ],
        [
            -14.96,
            15.25
        ]
    ],
    "Profile_lines": [
        [
            [
                -2.42,
                6.64
            ],
            [
                -0.31,
                11.18
            ]
        ],
        [
            [
                -0.31,
                11.18
            ],
            [
                -13.9,
                17.52
            ]
        ],
        [
            [
                -13.9,
                17.52
            ],
            [
                -16.01,
                12.98
            ]
        ],
        [
            [
                -16.01,
                12.98
            ],
            [
                -2.42,
                6.64
            ]
        ]
    ],
    "Midcurve_lines": [
        [
            [
                -1.36,
                8.91
            ],
            [
                -14.96,
                15.25
            ]
        ]
    ]
}