{
    "ShapeName": "I_translated_-6",
    "Profile": [
        [
            -1.0,
            -1.0
        ],
        [
            4.0,
            -1.0
        ],
        [
            4.0,
            14.0
        ],
        [
            -1.0,
            14.0
        ]
    ],
    "Midcurve": [
        [
            1.5,
            -1.0
        ],
        [
            1.5,
            14.0
        ]
    ],
    "Profile_lines": [
        [
            [
                -1.0,
                -1.0
            ],
            [
                4.0,
                -1.0
            ]
        ],
        [
            [
                4.0,
                -1.0
            ],
            [
                4.0,
                14.0
            ]
        ],
        [
            [
                4.0,
                14.0
            ],
            [
                -1.0,
                14.0
            ]
        ],
        [
            [
                -1.0,
                14.0
            ],
            [
                -1.0,
                -1.0
            ]
        ]
    ],
    "Midcurve_lines": [
        [
            [
                1.5,
                -1.0
            ],
            [
                1.5,
                14.0
            ]
        ]
    ]
}