{
    "ShapeName": "I_translated_36",
    "Profile": [
        [
            41.0,
            41.0
        ],
        [
            46.0,
            41.0
        ],
        [
            46.0,
            56.0
        ],
        [
            41.0,
            56.0
        ]
    ],
    "Midcurve": [
        [
            43.5,
            41.0
        ],
        [
            43.5,
            56.0
        ]
    ],
    "Profile_lines": [
        [
            [
                41.0,
                41.0
            ],
            [
                46.0,
                41.0
            ]
        ],
        [
            [
                46.0,
                41.0
            ],
            [
                46.0,
                56.0
            ]
        ],
        [
            [
                46.0,
                56.0
            ],
            [
                41.0,
                56.0
            ]
        ],
        [
            [
                41.0,
                56.0
            ],
            [
                41.0,
                41.0
            ]
        ]
    ],
    "Midcurve_lines": [
        [
            [
                43.5,
                41.0
            ],
            [
                43.5,
                56.0
            ]
        ]
    ]
}