{
    "ShapeName": "L_rotated_139",
    "Profile": [
        [
            -7.05,
            -0.49
        ],
        [
            -10.83,
            2.79
        ],
        [
            -27.23,
            -16.08
        ],
        [
            -46.1,
            0.32
        ],
        [
            -49.38,
            -3.45
        ],
        [
            -26.74,
            -23.13
        ]
    ],
    "Midcurve": [
        [
            -8.94,
            1.15
        ],
        [
            -26.98,
            -19.61
        ],
        [
            -47.74,
            -1.57
        ]
    ],
    "Profile_lines": [
        [
            [
                -7.05,
                -0.49
            ],
            [
                -10.83,
                2.79
            ]
        ],
        [
            [
                -10.83,
                2.79
            ],
            [
                -27.23,
                -16.08
            ]
        ],
        [
            [
                -27.23,
                -16.08
            ],
            [
                -46.1,
                0.32
            ]
        ],
        [
            [
                -46.1,
                0.32
            ],
            [
                -49.38,
                -3.45
            ]
        ],
        [
            [
                -49.38,
                -3.45
            ],
            [
                -26.74,
                -23.13
            ]
        ],
        [
            [
                -26.74,
                -23.13
            ],
            [
                -7.05,
                -0.49
            ]
        ]
    ],
    "Midcurve_lines": [
        [
            [
                -8.94,
                1.15
            ],
            [
                -26.98,
                -19.61
            ]
        ],
        [
            [
                -26.98,
                -19.61
            ],
            [
                -47.74,
                -1.57
            ]
        ]
    ]
}