{
    "ShapeName": "L_rotated_73",
    "Profile": [
        [
            -3.32,
            6.24
        ],
        [
            -1.86,
            11.02
        ],
        [
            -25.77,
            18.33
        ],
        [
            -18.46,
            42.24
        ],
        [
            -23.24,
            43.7
        ],
        [
            -32.01,
            15.01
        ]
    ],
    "Midcurve": [
        [
            -2.59,
            8.63
        ],
        [
            -28.89,
            16.67
        ],
        [
            -20.85,
            42.97
        ]
    ],
    "Profile_lines": [
        [
            [
                -3.32,
                6.24
            ],
            [
                -1.86,
                11.02
            ]
        ],
        [
            [
                -1.86,
                11.02
            ],
            [
                -25.77,
                18.33
            ]
        ],
        [
            [
                -25.77,
                18.33
            ],
            [
                -18.46,
                42.24
            ]
        ],
        [
            [
                -18.46,
                42.24
            ],
            [
                -23.24,
                43.7
            ]
        ],
        [
            [
                -23.24,
                43.7
            ],
            [
                -32.01,
                15.01
            ]
        ],
        [
            [
                -32.01,
                15.01
            ],
            [
                -3.32,
                6.24
            ]
        ]
    ],
    "Midcurve_lines": [
        [
            [
                -2.59,
                8.63
            ],
            [
                -28.89,
                16.67
            ]
        ],
        [
            [
                -28.89,
                16.67
            ],
            [
                -20.85,
                42.97
            ]
        ]
    ]
}