{
    "ShapeName": "L_rotated_83",
    "Profile": [
        [
            -4.35,
            5.57
        ],
        [
            -3.74,
            10.53
        ],
        [
            -28.56,
            13.58
        ],
        [
            -25.51,
            38.4
        ],
        [
            -30.47,
            39.0
        ],
        [
            -34.13,
            9.23
        ]
    ],
    "Midcurve": [
        [
            -4.05,
            8.05
        ],
        [
            -31.34,
            11.4
        ],
        [
            -27.99,
            38.7
        ]
    ],
    "Profile_lines": [
        [
            [
                -4.35,
                5.57
            ],
            [
                -3.74,
                10.53
            ]
        ],
        [
            [
                -3.74,
                10.53
            ],
            [
                -28.56,
                13.58
            ]
        ],
        [
            [
                -28.56,
                13.58
            ],
            [
                -25.51,
                38.4
            ]
        ],
        [
            [
                -25.51,
                38.4
            ],
            [
                -30.47,
                39.0
            ]
        ],
        [
            [
                -30.47,
                39.0
            ],
            [
                -34.13,
                9.23
            ]
        ],
        [
            [
                -34.13,
                9.23
            ],
            [
                -4.35,
                5.57
            ]
        ]
    ],
    "Midcurve_lines": [
        [
            [
                -4.05,
                8.05
            ],
            [
                -31.34,
                11.4
            ]
        ],
        [
            [
                -31.34,
                11.4
            ],
            [
                -27.99,
                38.7
            ]
        ]
    ]
}