{
    "ShapeName": "L_rotated_126",
    "Profile": [
        [
            -6.98,
            1.11
        ],
        [
            -9.92,
            5.15
        ],
        [
            -30.15,
            -9.54
        ],
        [
            -44.84,
            10.68
        ],
        [
            -48.89,
            7.74
        ],
        [
            -31.25,
            -16.53
        ]
    ],
    "Midcurve": [
        [
            -8.45,
            3.13
        ],
        [
            -30.7,
            -13.04
        ],
        [
            -46.87,
            9.21
        ]
    ],
    "Profile_lines": [
        [
            [
                -6.98,
                1.11
            ],
            [
                -9.92,
                5.15
            ]
        ],
        [
            [
                -9.92,
                5.15
            ],
            [
                -30.15,
                -9.54
            ]
        ],
        [
            [
                -30.15,
                -9.54
            ],
            [
                -44.84,
                10.68
            ]
        ],
        [
            [
                -44.84,
                10.68
            ],
            [
                -48.89,
                7.74
            ]
        ],
        [
            [
                -48.89,
                7.74
            ],
            [
                -31.25,
                -16.53
            ]
        ],
        [
            [
                -31.25,
                -16.53
            ],
            [
                -6.98,
                1.11
            ]
        ]
    ],
    "Midcurve_lines": [
        [
            [
                -8.45,
                3.13
            ],
            [
                -30.7,
                -13.04
            ]
        ],
        [
            [
                -30.7,
                -13.04
            ],
            [
                -46.87,
                9.21
            ]
        ]
    ]
}