{
    "ShapeName": "L_translated_20",
    "Profile": [
        [
            25.0,
            25.0
        ],
        [
            30.0,
            25.0
        ],
        [
            30.0,
            50.0
        ],
        [
            55.0,
            50.0
        ],
        [
            55.0,
            55.0
        ],
        [
            25.0,
            55.0
        ]
    ],
    "Midcurve": [
        [
            27.5,
            25.0
        ],
        [
            27.5,
            52.5
        ],
        [
            55.0,
            52.5
        ]
    ],
    "Profile_lines": [
        [
            [
                25.0,
                25.0
            ],
            [
                30.0,
                25.0
            ]
        ],
        [
            [
                30.0,
                25.0
            ],
            [
                30.0,
                50.0
            ]
        ],
        [
            [
                30.0,
                50.0
            ],
            [
                55.0,
                50.0
            ]
        ],
        [
            [
                55.0,
                50.0
            ],
            [
                55.0,
                55.0
            ]
        ],
        [
            [
                55.0,
                55.0
            ],
            [
                25.0,
                55.0
            ]
        ],
        [
            [
                25.0,
                55.0
            ],
            [
                25.0,
                25.0
            ]
        ]
    ],
    "Midcurve_lines": [
        [
            [
                27.5,
                25.0
            ],
            [
                27.5,
                52.5
            ]
        ],
        [
            [
                27.5,
                52.5
            ],
            [
                55.0,
                52.5
            ]
        ]
    ]
}