{
    "ShapeName": "Plus_rotated_92",
    "Profile": [
        [
            -24.98,
            -0.87
        ],
        [
            -25.33,
            9.12
        ],
        [
            -45.32,
            8.42
        ],
        [
            -45.5,
            13.42
        ],
        [
            -25.51,
            14.12
        ],
        [
            -25.86,
            24.11
        ],
        [
            -20.86,
            24.29
        ],
        [
            -20.51,
            14.29
        ],
        [
            -0.52,
            14.99
        ],
        [
            -0.35,
            9.99
        ],
        [
            -20.34,
            9.3
        ],
        [
            -19.99,
            -0.7
        ]
    ],
    "Midcurve": [
        [
            -0.44,
            12.49
        ],
        [
            -22.92,
            11.71
        ],
        [
            -45.41,
            10.92
        ],
        [
            -22.92,
            11.71
        ],
        [
            -22.49,
            -0.79
        ],
        [
            -23.36,
            24.2
        ]
    ],
    "Profile_lines": [
        [
            [
                -24.98,
                -0.87
            ],
            [
                -25.33,
                9.12
            ]
        ],
        [
            [
                -25.33,
                9.12
            ],
            [
                -45.32,
                8.42
            ]
        ],
        [
            [
                -45.32,
                8.42
            ],
            [
                -45.5,
                13.42
            ]
        ],
        [
            [
                -45.5,
                13.42
            ],
            [
                -25.51,
                14.12
            ]
        ],
        [
            [
                -25.51,
                14.12
            ],
            [
                -25.86,
                24.11
            ]
        ],
        [
            [
                -25.86,
                24.11
            ],
            [
                -20.86,
                24.29
            ]
        ],
        [
            [
                -20.86,
                24.29
            ],
            [
                -20.51,
                14.29
            ]
        ],
        [
            [
                -20.51,
                14.29
            ],
            [
                -0.52,
                14.99
            ]
        ],
        [
            [
                -0.52,
                14.99
            ],
            [
                -0.35,
                9.99
            ]
        ],
        [
            [
                -0.35,
                9.99
            ],
            [
                -20.34,
                9.3
            ]
        ],
        [
            [
                -20.34,
                9.3
            ],
            [
                -19.99,
                -0.7
            ]
        ],
        [
            [
                -19.99,
                -0.7
            ],
            [
                -24.98,
                -0.87
            ]
        ]
    ],
    "Midcurve_lines": [
        [
            [
                -0.44,
                12.49
            ],
            [
                -22.92,
                11.71
            ]
        ],
        [
            [
                -22.92,
                11.71
            ],
            [
                -45.41,
                10.92
            ]
        ],
        [
            [
                -45.41,
                10.92
            ],
            [
                -22.92,
                11.71
            ]
        ],
        [
            [
                -22.92,
                11.71
            ],
            [
                -22.49,
                -0.79
            ]
        ],
        [
            [
                -22.49,
                -0.79
            ],
            [
                -23.36,
                24.2
            ]
        ]
    ]
}