{
    "ShapeName": "Plus_rotated_142",
    "Profile": [
        [
            -15.39,
            -19.7
        ],
        [
            -23.27,
            -13.54
        ],
        [
            -35.58,
            -29.3
        ],
        [
            -39.52,
            -26.23
        ],
        [
            -27.21,
            -10.47
        ],
        [
            -35.09,
            -4.31
        ],
        [
            -32.01,
            -0.37
        ],
        [
            -24.13,
            -6.53
        ],
        [
            -11.82,
            9.23
        ],
        [
            -7.88,
            6.16
        ],
        [
            -20.19,
            -9.6
        ],
        [
            -12.31,
            -15.76
        ]
    ],
    "Midcurve": [
        [
            -9.85,
            7.7
        ],
        [
            -23.7,
            -10.03
        ],
        [
            -37.55,
            -27.76
        ],
        [
            -23.7,
            -10.03
        ],
        [
            -13.85,
            -17.73
        ],
        [
            -33.55,
            -2.34
        ]
    ],
    "Profile_lines": [
        [
            [
                -15.39,
                -19.7
            ],
            [
                -23.27,
                -13.54
            ]
        ],
        [
            [
                -23.27,
                -13.54
            ],
            [
                -35.58,
                -29.3
            ]
        ],
        [
            [
                -35.58,
                -29.3
            ],
            [
                -39.52,
                -26.23
            ]
        ],
        [
            [
                -39.52,
                -26.23
            ],
            [
                -27.21,
                -10.47
            ]
        ],
        [
            [
                -27.21,
                -10.47
            ],
            [
                -35.09,
                -4.31
            ]
        ],
        [
            [
                -35.09,
                -4.31
            ],
            [
                -32.01,
                -0.37
            ]
        ],
        [
            [
                -32.01,
                -0.37
            ],
            [
                -24.13,
                -6.53
            ]
        ],
        [
            [
                -24.13,
                -6.53
            ],
            [
                -11.82,
                9.23
            ]
        ],
        [
            [
                -11.82,
                9.23
            ],
            [
                -7.88,
                6.16
            ]
        ],
        [
            [
                -7.88,
                6.16
            ],
            [
                -20.19,
                -9.6
            ]
        ],
        [
            [
                -20.19,
                -9.6
            ],
            [
                -12.31,
                -15.76
            ]
        ],
        [
            [
                -12.31,
                -15.76
            ],
            [
                -15.39,
                -19.7
            ]
        ]
    ],
    "Midcurve_lines": [
        [
            [
                -9.85,
                7.7
            ],
            [
                -23.7,
                -10.03
            ]
        ],
        [
            [
                -23.7,
                -10.03
            ],
            [
                -37.55,
                -27.76
            ]
        ],
        [
            [
                -37.55,
                -27.76
            ],
            [
                -23.7,
                -10.03
            ]
        ],
        [
            [
                -23.7,
                -10.03
            ],
            [
                -13.85,
                -17.73
            ]
        ],
        [
            [
                -13.85,
                -17.73
            ],
            [
                -33.55,
                -2.34
            ]
        ]
    ]
}