{
    "ShapeName": "Plus_rotated_84",
    "Profile": [
        [
            -24.86,
            2.61
        ],
        [
            -23.82,
            12.56
        ],
        [
            -43.71,
            14.65
        ],
        [
            -43.19,
            19.62
        ],
        [
            -23.3,
            17.53
        ],
        [
            -22.25,
            27.48
        ],
        [
            -17.28,
            26.95
        ],
        [
            -18.32,
            17.01
        ],
        [
            1.57,
            14.92
        ],
        [
            1.05,
            9.95
        ],
        [
            -18.85,
            12.04
        ],
        [
            -19.89,
            2.09
        ]
    ],
    "Midcurve": [
        [
            1.31,
            12.43
        ],
        [
            -21.07,
            14.78
        ],
        [
            -43.45,
            17.14
        ],
        [
            -21.07,
            14.78
        ],
        [
            -22.38,
            2.35
        ],
        [
            -19.76,
            27.21
        ]
    ],
    "Profile_lines": [
        [
            [
                -24.86,
                2.61
            ],
            [
                -23.82,
                12.56
            ]
        ],
        [
            [
                -23.82,
                12.56
            ],
            [
                -43.71,
                14.65
            ]
        ],
        [
            [
                -43.71,
                14.65
            ],
            [
                -43.19,
                19.62
            ]
        ],
        [
            [
                -43.19,
                19.62
            ],
            [
                -23.3,
                17.53
            ]
        ],
        [
            [
                -23.3,
                17.53
            ],
            [
                -22.25,
                27.48
            ]
        ],
        [
            [
                -22.25,
                27.48
            ],
            [
                -17.28,
                26.95
            ]
        ],
        [
            [
                -17.28,
                26.95
            ],
            [
                -18.32,
                17.01
            ]
        ],
        [
            [
                -18.32,
                17.01
            ],
            [
                1.57,
                14.92
            ]
        ],
        [
            [
                1.57,
                14.92
            ],
            [
                1.05,
                9.95
            ]
        ],
        [
            [
                1.05,
                9.95
            ],
            [
                -18.85,
                12.04
            ]
        ],
        [
            [
                -18.85,
                12.04
            ],
            [
                -19.89,
                2.09
            ]
        ],
        [
            [
                -19.89,
                2.09
            ],
            [
                -24.86,
                2.61
            ]
        ]
    ],
    "Midcurve_lines": [
        [
            [
                1.31,
                12.43
            ],
            [
                -21.07,
                14.78
            ]
        ],
        [
            [
                -21.07,
                14.78
            ],
            [
                -43.45,
                17.14
            ]
        ],
        [
            [
                -43.45,
                17.14
            ],
            [
                -21.07,
                14.78
            ]
        ],
        [
            [
                -21.07,
                14.78
            ],
            [
                -22.38,
                2.35
            ]
        ],
        [
            [
                -22.38,
                2.35
            ],
            [
                -19.76,
                27.21
            ]
        ]
    ]
}