{
    "ShapeName": "Plus_rotated_168",
    "Profile": [
        [
            -5.2,
            -24.45
        ],
        [
            -14.98,
            -22.37
        ],
        [
            -19.14,
            -41.94
        ],
        [
            -24.03,
            -40.9
        ],
        [
            -19.87,
            -21.34
        ],
        [
            -29.65,
            -19.26
        ],
        [
            -28.61,
            -14.37
        ],
        [
            -18.83,
            -16.44
        ],
        [
            -14.67,
            3.12
        ],
        [
            -9.78,
            2.08
        ],
        [
            -13.94,
            -17.48
        ],
        [
            -4.16,
            -19.56
        ]
    ],
    "Midcurve": [
        [
            -12.23,
            2.6
        ],
        [
            -16.9,
            -19.41
        ],
        [
            -21.58,
            -41.42
        ],
        [
            -16.9,
            -19.41
        ],
        [
            -4.68,
            -22.01
        ],
        [
            -29.13,
            -16.81
        ]
    ],
    "Profile_lines": [
        [
            [
                -5.2,
                -24.45
            ],
            [
                -14.98,
                -22.37
            ]
        ],
        [
            [
                -14.98,
                -22.37
            ],
            [
                -19.14,
                -41.94
            ]
        ],
        [
            [
                -19.14,
                -41.94
            ],
            [
                -24.03,
                -40.9
            ]
        ],
        [
            [
                -24.03,
                -40.9
            ],
            [
                -19.87,
                -21.34
            ]
        ],
        [
            [
                -19.87,
                -21.34
            ],
            [
                -29.65,
                -19.26
            ]
        ],
        [
            [
                -29.65,
                -19.26
            ],
            [
                -28.61,
                -14.37
            ]
        ],
        [
            [
                -28.61,
                -14.37
            ],
            [
                -18.83,
                -16.44
            ]
        ],
        [
            [
                -18.83,
                -16.44
            ],
            [
                -14.67,
                3.12
            ]
        ],
        [
            [
                -14.67,
                3.12
            ],
            [
                -9.78,
                2.08
            ]
        ],
        [
            [
                -9.78,
                2.08
            ],
            [
                -13.94,
                -17.48
            ]
        ],
        [
            [
                -13.94,
                -17.48
            ],
            [
                -4.16,
                -19.56
            ]
        ],
        [
            [
                -4.16,
                -19.56
            ],
            [
                -5.2,
                -24.45
            ]
        ]
    ],
    "Midcurve_lines": [
        [
            [
                -12.23,
                2.6
            ],
            [
                -16.9,
                -19.41
            ]
        ],
        [
            [
                -16.9,
                -19.41
            ],
            [
                -21.58,
                -41.42
            ]
        ],
        [
            [
                -21.58,
                -41.42
            ],
            [
                -16.9,
                -19.41
            ]
        ],
        [
            [
                -16.9,
                -19.41
            ],
            [
                -4.68,
                -22.01
            ]
        ],
        [
            [
                -4.68,
                -22.01
            ],
            [
                -29.13,
                -16.81
            ]
        ]
    ]
}